nsfw_detector/__init__.py
nsfw_detector/predict.py
nsfw_detector-1.1.1.dist-info/LICENSE.md
nsfw_detector-1.1.1.dist-info/METADATA
nsfw_detector-1.1.1.dist-info/WHEEL
nsfw_detector-1.1.1.dist-info/entry_points.txt
nsfw_detector-1.1.1.dist-info/top_level.txt
nsfw_detector-1.1.1.dist-info/RECORD
