Metadata-Version: 2.1
Name: nsfw-detector
Version: 1.1.1
Summary: NSFW Image Detection with Deep Learning
Home-page: https://github.com/GantMan/nsfw_model
Author: Prakhar Baveja
Author-email: prakhar.baveja@gmail.com
License: GPLv3
Platform: UNKNOWN
Classifier: License :: OSI Approved :: GNU General Public License v3 (GPLv3)
Classifier: Programming Language :: Python
Classifier: Programming Language :: Python :: 3
Classifier: Programming Language :: Python :: 3.6
Classifier: Programming Language :: Python :: Implementation :: CPython
Classifier: Programming Language :: Python :: Implementation :: PyPy
Requires-Python: >=3.5.0
